lightweight_environ.py
lightweight_environ-0.1.1.dist-info/LICENCE
lightweight_environ-0.1.1.dist-info/METADATA
lightweight_environ-0.1.1.dist-info/WHEEL
lightweight_environ-0.1.1.dist-info/top_level.txt
lightweight_environ-0.1.1.dist-info/RECORD
