Metadata-Version: 2.1
Name: lightweight-environ
Version: 0.1.1
Summary: Simple and lightweight environment variable ingestion
Home-page: https://github.com/cursive-works/lightweight-environ
Author: Patrick Smith
License: MIT
Keywords: environment variables,configuration
Classifier: Topic :: Utilities
Classifier: Intended Audience :: Developers
Classifier: Operating System :: OS Independent
Classifier: Topic :: Software Development :: Libraries :: Python Modules
Classifier: Programming Language :: Python
Classifier: Programming Language :: Python :: 3
Classifier: Programming Language :: Python :: 3.7
Classifier: Programming Language :: Python :: 3.8
Classifier: Programming Language :: Python :: 3.9
Classifier: Programming Language :: Python :: 3.10
Classifier: License :: OSI Approved :: MIT License
Requires-Python: >=3.7
License-File: LICENCE
